cryohub/__init__.py
cryohub/_version.py
cryohub/cli.py
cryohub/conftest.py
cryohub/reading/__init__.py
cryohub/reading/box.py
cryohub/reading/cbox.py
cryohub/reading/em.py
cryohub/reading/eman2_hdf.py
cryohub/reading/eman2_json.py
cryohub/reading/main.py
cryohub/reading/mrc.py
cryohub/reading/star.py
cryohub/reading/tbl.py
cryohub/reading/tif.py
cryohub/reading/_tests/__init__.py
cryohub/reading/_tests/test_read.py
cryohub/reading/_tests/test_read_em.py
cryohub/reading/_tests/test_read_hdf.py
cryohub/reading/_tests/test_read_mrc.py
cryohub/reading/_tests/test_read_star.py
cryohub/reading/_tests/test_read_tbl.py
cryohub/utils/__init__.py
cryohub/utils/constants.py
cryohub/utils/generic.py
cryohub/utils/star.py
cryohub/utils/testing.py
cryohub/utils/types.py
cryohub/writing/__init__.py
cryohub/writing/em.py
cryohub/writing/hdf.py
cryohub/writing/main.py
cryohub/writing/mrc.py
cryohub/writing/star.py
cryohub/writing/tbl.py
cryohub/writing/_tests/__init__.py
cryohub/writing/_tests/test_write.py
cryohub/writing/_tests/test_write_em.py
cryohub/writing/_tests/test_write_mrc.py
cryohub/writing/_tests/test_write_star.py
cryohub/writing/_tests/test_write_tbl.py
cryohub-0.6.4.dist-info/LICENSE
cryohub-0.6.4.dist-info/METADATA
cryohub-0.6.4.dist-info/WHEEL
cryohub-0.6.4.dist-info/entry_points.txt
cryohub-0.6.4.dist-info/top_level.txt
cryohub-0.6.4.dist-info/RECORD
