Metadata-Version: 2.1
Name: cryohub
Version: 0.6.4
Summary: IO hub for Cryo-EM, Cryo-ET and subtomogram averaging data.
Home-page: https://github.com/teamtomo/cryohub
Download-URL: https://github.com/teamtomo/cryohub
Author: Blik Team
Author-email: blik-team@googlegroups.com
License: GNU General Public License v3 (GPLv3)
Project-URL: Bug Tracker, https://github.com/teamtomo/cryohub/issues
Project-URL: Documentation, https://github.com/teamtomo/cryohub#README.md
Project-URL: Source Code, https://github.com/teamtomo/cryohub
Project-URL: Changelog, https://github.com/teamtomo/cryohub/blob/main/CHANGELOG.md
Classifier: Development Status :: 2 - Pre-Alpha
Classifier: Environment :: X11 Applications :: Qt
Classifier: Intended Audience :: Education
Classifier: Intended Audience :: Science/Research
Classifier: License :: OSI Approved :: GNU General Public License v3 (GPLv3)
Classifier: Programming Language :: Python
Classifier: Programming Language :: Python :: 3 :: Only
Classifier: Programming Language :: Python :: 3.8
Classifier: Programming Language :: Python :: 3.9
Classifier: Programming Language :: Python :: 3.10
Classifier: Topic :: Scientific/Engineering
Classifier: Topic :: Scientific/Engineering :: Visualization
Classifier: Topic :: Scientific/Engineering :: Information Analysis
Classifier: Topic :: Scientific/Engineering :: Bio-Informatics
Classifier: Topic :: Utilities
Requires-Python: >=3.8
License-File: LICENSE
Requires-Dist: click
Requires-Dist: cryotypes >=0.2.0
Requires-Dist: dask
Requires-Dist: dynamotable >=0.2.4
Requires-Dist: emfile >=0.3
Requires-Dist: h5py
Requires-Dist: imagecodecs
Requires-Dist: ipython
Requires-Dist: mrcfile >=1.3.0
Requires-Dist: numpy
Requires-Dist: pandas
Requires-Dist: pydantic
Requires-Dist: scipy
Requires-Dist: starfile >=0.5.0
Requires-Dist: tifffile
Requires-Dist: zarr
Provides-Extra: dev
Requires-Dist: black ; extra == 'dev'
Requires-Dist: flake8 ; extra == 'dev'
Requires-Dist: ipython ; extra == 'dev'
Requires-Dist: isort ; extra == 'dev'
Requires-Dist: pre-commit ; extra == 'dev'
Requires-Dist: pytest ; extra == 'dev'
Requires-Dist: pytest-cov ; extra == 'dev'
Requires-Dist: tox ; extra == 'dev'
